py_msgraph/__init__.py
py_msgraph/msgraph.py
py_msgraph-0.0.4.dist-info/licenses/LICENSE
py_msgraph-0.0.4.dist-info/METADATA
py_msgraph-0.0.4.dist-info/WHEEL
py_msgraph-0.0.4.dist-info/top_level.txt
py_msgraph-0.0.4.dist-info/RECORD
