Metadata-Version: 2.4
Name: py-msgraph
Version: 0.0.4
Summary: library to use MS graph API
Author-email: Sungwon Um <shineum@gmail.com>
License: The MIT License (MIT)
Project-URL: Homepage, https://github.com/shineum/py-msgraph
Keywords: microsoft,graph api
Classifier: License :: OSI Approved :: MIT License
Classifier: Programming Language :: Python
Classifier: Programming Language :: Python :: 3
Requires-Python: >=3.7
License-File: LICENSE
Dynamic: license-file
